[
    {
        "id": "1",
        "name": "Donec tempus pretium arcu ",
        "Price": "12$",
        "description": "Medical Term (medical dictionary) is the medical terminology for MedicineNet.com.",
        "img": "https://i.ibb.co/6wx6CjV/product-04-300x300.jpg"
    },
    {
        "id": "2",
        "name": "Cillum dolore tortor nisl",
        "Price": "22$",
        "description": "Medical Term (medical dictionary) is the medical terminology for MedicineNet.com. Our doctors define difficult medical language in easy-to-understand explanations of over 19,000 medical terms.",
        "img": "https://i.ibb.co/Js5YCWW/product-03-300x300.jpg"
    },
    {
        "id": "3",
        "name": "Epicuri per lobortis eleifend",
        "Price": "32$",
        "description": "Medical Term (medical dictionary) is the medical terminology for MedicineNet.com. Our doctors define difficult medical language in easy-to-understand explanations of over 19,000 medical terms.",
        "img": "https://i.ibb.co/NnLbxLv/product-10-300x300.jpg"
    },
    {
        "id": "4",
        "name": "Nullam maximus eget nisi",
        "Price": "12$",
        "description": "Medical Term (medical dictionary) is the medical terminology for MedicineNet.com. Our doctors define difficult medical language in easy-to-understand explanations of over 19,000 medical terms.",
        "img": "https://i.ibb.co/nDS6fQr/product-13-300x300.jpg"
    },
    {
        "id": "5",
        "name": "Nullam maximus eget nisi",
        "Price": "122$",
        "description": "Medical Term (medical dictionary) is the medical terminology for MedicineNet.com. Our doctors define difficult medical language in easy-to-understand explanations of over 19,000 medical terms.",
        "img": "https://i.ibb.co/XSLLLsp/product-14-300x300.jpg"
    },
    {
        "id": "5",
        "name": "Laudantium enim fringilla",
        "Price": "122$",
        "description": "Medical Term (medical dictionary) is the medical terminology for MedicineNet.com. Our doctors define difficult medical language in easy-to-understand explanations of over 19,000 medical terms.",
        "img": "https://i.ibb.co/9tCGnqL/product-16-300x300.jpg"
    }
]